<COURSE>
	<CLOSEDNAVIGATION>false</CLOSEDNAVIGATION>
	<DISABLEDNEXT>false</DISABLEDNEXT>
	<ONLYASSESSMENTLOCK>true</ONLYASSESSMENTLOCK>
	<DISABLEDSLIDER>false</DISABLEDSLIDER>
    <ALLOWFULLSCREEN>true</ALLOWFULLSCREEN>
    <SHOWINTROSCREEN>true</SHOWINTROSCREEN>
    <SHOWHOMESCREEN>false</SHOWHOMESCREEN>
    <SHOWXYCORDINATE>false</SHOWXYCORDINATE>
    <ISREFERENCES>true</ISREFERENCES>
	<RemovePageAnimation>false</RemovePageAnimation>
	<isPageCompletionOnPageLoad>false</isPageCompletionOnPageLoad>
	<COURSETITLE><![CDATA[Sugar]]></COURSETITLE>
	<MODULE ID="M1" SHOWINMENU="" ISDISABLEINMENU="">
		<MODULETITLE><![CDATA[Sugar and Safe Care]]></MODULETITLE>
		<LESSON ID="M1L0" SHOWINMENU="" ISDISABLEINMENU="">
			<LESSONTITLE><![CDATA[Sugar and Safe Care]]></LESSONTITLE>

			<TOPIC ID="M1L0T1" SHOWINMENU="" ISDISABLEINMENU="">
				<TOPICTITLE><![CDATA[Sugar and Safe Care]]></TOPICTITLE>

				<PAGE pageID="1"  ID="M1L0T1P0" PAGETYPE = "staic" SHOWINMENU="" ISDISABLEINMENU="" XMLSRC="" PAGESRC="pages/Topic01/T01P00.html" AUDIODISABLE="" BACKDISABLE="T" NEXTDISABLE="" TRANSCRIPTDISABLE="" PLAYPAUSEDISABLE="" ISSKILLCHECK="" MAXCONDITION="0" SHOWLOGO="F">
					<PAGETITLE><![CDATA[Introduction to Sugar and Safe Care]]></PAGETITLE>
				</PAGE>

				<PAGE ID="M1L0T1P1"  PAGETYPE = "staic" pageID="2"  SHOWINMENU="" ISDISABLEINMENU="" XMLSRC="" PAGESRC="pages/Topic01/T01P01.html" AUDIODISABLE="" BACKDISABLE="" NEXTDISABLE="" TRANSCRIPTDISABLE="" PLAYPAUSEDISABLE="" ISSKILLCHECK="" MAXCONDITION="0" SHOWLOGO="F">
					<PAGETITLE><![CDATA[Module Objectives]]></PAGETITLE>
				</PAGE>

				<PAGE ID="M1L0T1P2" PAGETYPE = "staic" pageID="3"  SHOWINMENU="" ISDISABLEINMENU="" XMLSRC="" PAGESRC="pages/Topic01/T01P02.html" AUDIODISABLE="" BACKDISABLE="" NEXTDISABLE="" TRANSCRIPTDISABLE="" PLAYPAUSEDISABLE="" ISSKILLCHECK="" MAXCONDITION="0" SHOWLOGO="F">
					<PAGETITLE><![CDATA[The S.T.A.B.L.E. Hospital]]></PAGETITLE>
				</PAGE>

				<PAGE ID="M1L0T1P3" PAGETYPE = "staic" pageID="4"  SHOWINMENU="" ISDISABLEINMENU="" XMLSRC="pages/Topic01/xml/T01P02.xml" PAGESRC="pages/Topic01/T01P03.html" AUDIODISABLE="" BACKDISABLE="" NEXTDISABLE="" TRANSCRIPTDISABLE="" PLAYPAUSEDISABLE="" ISSKILLCHECK="" MAXCONDITION="0" SHOWLOGO="F">
					<PAGETITLE><![CDATA[The S.T.A.B.L.E. Hospital]]></PAGETITLE>
				</PAGE>

				<PAGE ID="M1L0T1P4" pageID="5" PAGETYPE = "staic"  SHOWINMENU="" ISDISABLEINMENU="" XMLSRC="pages/Topic01/xml/T01P02.xml" PAGESRC="pages/Topic01/T01P05.html" AUDIODISABLE="" BACKDISABLE="" NEXTDISABLE="" TRANSCRIPTDISABLE="" PLAYPAUSEDISABLE="" ISSKILLCHECK="" MAXCONDITION="0" SHOWLOGO="F">
					<PAGETITLE><![CDATA[The S.T.A.B.L.E. Hospital]]></PAGETITLE>
				</PAGE>

				<PAGE ID="M1L0T1P5" PAGETYPE = "staic" pageID="6"  SHOWINMENU="" ISDISABLEINMENU="" XMLSRC="pages/Topic01/xml/T01P02.xml" PAGESRC="pages/Topic01/T01P04.html" AUDIODISABLE="" BACKDISABLE="" NEXTDISABLE="" TRANSCRIPTDISABLE="" PLAYPAUSEDISABLE="" ISSKILLCHECK="" MAXCONDITION="0" SHOWLOGO="F">
					<PAGETITLE><![CDATA[The S.T.A.B.L.E. Hospital]]></PAGETITLE>
				</PAGE>

				<PAGE ID="M1L0T1P6" pageID="7"  PAGETYPE = "staic" SHOWINMENU="" ISDISABLEINMENU="" XMLSRC="pages/Topic01/xml/T01P02.xml" PAGESRC="pages/Topic01/T01P06.html" AUDIODISABLE="" BACKDISABLE="" NEXTDISABLE="" TRANSCRIPTDISABLE="" PLAYPAUSEDISABLE="" ISSKILLCHECK="" MAXCONDITION="0" SHOWLOGO="F">
					<PAGETITLE><![CDATA[The S.T.A.B.L.E. Hospital]]></PAGETITLE>
				</PAGE>

				<PAGE ID="M1L0T1P7" pageID="8" PAGETYPE = "lockedPage"  SHOWINMENU="" ISDISABLEINMENU="" XMLSRC="" PAGESRC="pages/Topic01/T01P07.html" AUDIODISABLE="" BACKDISABLE="" NEXTDISABLE="" TRANSCRIPTDISABLE="" PLAYPAUSEDISABLE="" ISSKILLCHECK="" MAXCONDITION="0" SHOWLOGO="F">
					<PAGETITLE><![CDATA[The S.T.A.B.L.E. Hospital]]></PAGETITLE>				
				</PAGE>

				<PAGE ID="M1L0T1P8" PAGETYPE = "staic"  pageID="9"  SHOWINMENU="" ISDISABLEINMENU="" XMLSRC="pages/Topic01/xml/T01P02.xml" PAGESRC="pages/Topic01/T01P08.html" AUDIODISABLE="" BACKDISABLE="" NEXTDISABLE="" TRANSCRIPTDISABLE="" PLAYPAUSEDISABLE="" ISSKILLCHECK="" MAXCONDITION="0" SHOWLOGO="F">
					<PAGETITLE><![CDATA[The S.T.A.B.L.E. Hospital]]></PAGETITLE>
				</PAGE>

				<!-- <PAGE ID="M1L0T1P9" pageID="1"  SHOWINMENU="" ISDISABLEINMENU="" XMLSRC="pages/Topic01/xml/T01P02.xml" PAGESRC="pages/Topic01/T01P09.html" AUDIODISABLE="" BACKDISABLE="" NEXTDISABLE="" TRANSCRIPTDISABLE="" PLAYPAUSEDISABLE="" ISSKILLCHECK="" MAXCONDITION="0" SHOWLOGO="F">
					<PAGETITLE><![CDATA[The S.T.A.B.L.E. Hospital]]></PAGETITLE>
				</PAGE> -->

				<PAGE ID="M1L0T1P10" pageID="10" PAGETYPE = "staic" SHOWINMENU="" ISDISABLEINMENU="" XMLSRC="pages/Topic01/xml/T01P02.xml" PAGESRC="pages/Topic01/T01P10.html" AUDIODISABLE="" BACKDISABLE="" NEXTDISABLE="" TRANSCRIPTDISABLE="" PLAYPAUSEDISABLE="" ISSKILLCHECK="" MAXCONDITION="0" SHOWLOGO="F">
					<PAGETITLE><![CDATA[The S.T.A.B.L.E. Hospital]]></PAGETITLE>
				</PAGE>

				<!-- <PAGE ID="M1L0T1P11" pageID="1"  SHOWINMENU="" ISDISABLEINMENU="" XMLSRC="" PAGESRC="pages/Topic01/T01P11.html" AUDIODISABLE="" BACKDISABLE="" NEXTDISABLE="" TRANSCRIPTDISABLE="" PLAYPAUSEDISABLE="" ISSKILLCHECK="" MAXCONDITION="0" SHOWLOGO="F">
					<PAGETITLE><![CDATA[The S.T.A.B.L.E. Hospital]]></PAGETITLE>
				</PAGE> -->

				<PAGE ID="M1L0T1P12" pageID="11" PAGETYPE = "staic" SHOWINMENU="" ISDISABLEINMENU="" XMLSRC="pages/Topic01/xml/T01P02.xml" PAGESRC="pages/Topic01/T01P12.html" AUDIODISABLE="" BACKDISABLE="" NEXTDISABLE="" TRANSCRIPTDISABLE="" PLAYPAUSEDISABLE="" ISSKILLCHECK="" MAXCONDITION="0" SHOWLOGO="F">
					<PAGETITLE><![CDATA[The S.T.A.B.L.E. Hospital]]></PAGETITLE>
				</PAGE>

				<PAGE ID="M1L0T1P13" PAGETYPE = "lockedPage" pageID="12"  SHOWINMENU="" ISDISABLEINMENU="" XMLSRC="" PAGESRC="pages/Topic01/T01P13.html" AUDIODISABLE="" BACKDISABLE="" NEXTDISABLE="" TRANSCRIPTDISABLE="" PLAYPAUSEDISABLE="" ISSKILLCHECK="" MAXCONDITION="0" SHOWLOGO="F">
					<PAGETITLE><![CDATA[The S.T.A.B.L.E. Hospital]]></PAGETITLE>
				</PAGE>

				<PAGE ID="M1L0T1P14" PAGETYPE = "staic" pageID="13"  SHOWINMENU="" ISDISABLEINMENU="" XMLSRC="" PAGESRC="pages/Topic01/T01P14.html" AUDIODISABLE="" BACKDISABLE="" NEXTDISABLE="" TRANSCRIPTDISABLE="" PLAYPAUSEDISABLE="" ISSKILLCHECK="" MAXCONDITION="0" SHOWLOGO="F">
					<PAGETITLE><![CDATA[The S.T.A.B.L.E. Hospital]]></PAGETITLE>
				</PAGE>

				<PAGE ID="M1L0T1P15" pageID="14" PAGETYPE = "staic"  SHOWINMENU="" ISDISABLEINMENU="" XMLSRC="" PAGESRC="pages/Topic01/T01P15.html" AUDIODISABLE="" BACKDISABLE="" NEXTDISABLE="" TRANSCRIPTDISABLE="" PLAYPAUSEDISABLE="" ISSKILLCHECK="" MAXCONDITION="0" SHOWLOGO="F">
					<PAGETITLE><![CDATA[General Guidelines]]></PAGETITLE>
				</PAGE>

				<PAGE ID="M1L0T1P16" pageID="15"  PAGETYPE = "staic" SHOWINMENU="" ISDISABLEINMENU="" XMLSRC="pages/Topic01/xml/T01P04.xml" PAGESRC="pages/Topic01/T01P16.html" AUDIODISABLE="" BACKDISABLE="" NEXTDISABLE="" TRANSCRIPTDISABLE="" PLAYPAUSEDISABLE="" ISSKILLCHECK="" MAXCONDITION="0" SHOWLOGO="F">
					<PAGETITLE><![CDATA[Guideline I: If Infant Is Sick, Avoid Enteral Feedings (Oral and Tube)]]></PAGETITLE>
				</PAGE>

				<PAGE ID="M1L0T1P16_1" pageID="16" PAGETYPE = "staic"  SHOWINMENU="" ISDISABLEINMENU="" XMLSRC="pages/Topic01/xml/T01P04.xml" PAGESRC="pages/Topic01/T01P16_1.html" AUDIODISABLE="" BACKDISABLE="" NEXTDISABLE="" TRANSCRIPTDISABLE="" PLAYPAUSEDISABLE="" ISSKILLCHECK="" MAXCONDITION="0" SHOWLOGO="F">
					<PAGETITLE><![CDATA[Guideline I: If Infant Is Sick, Avoid Enteral Feedings (Oral and Tube)]]></PAGETITLE>
				</PAGE>

				<PAGE ID="M1L0T1P16_2" pageID="17" PAGETYPE = "staic" SHOWINMENU="" ISDISABLEINMENU="" XMLSRC="pages/Topic01/xml/T01P04.xml" PAGESRC="pages/Topic01/T01P16_2.html" AUDIODISABLE="" BACKDISABLE="" NEXTDISABLE="" TRANSCRIPTDISABLE="" PLAYPAUSEDISABLE="" ISSKILLCHECK="" MAXCONDITION="0" SHOWLOGO="F">
					<PAGETITLE><![CDATA[Guideline I: If Infant Is Sick, Avoid Enteral Feedings (Oral and Tube)]]></PAGETITLE>
				</PAGE>

				<PAGE ID="M1L0T1P16_3" pageID="18"  PAGETYPE = "staic" SHOWINMENU="" ISDISABLEINMENU="" XMLSRC="pages/Topic01/xml/T01P04.xml" PAGESRC="pages/Topic01/T01P16_3.html" AUDIODISABLE="" BACKDISABLE="" NEXTDISABLE="" TRANSCRIPTDISABLE="" PLAYPAUSEDISABLE="" ISSKILLCHECK="" MAXCONDITION="0" SHOWLOGO="F">
					<PAGETITLE><![CDATA[Guideline I: If Infant Is Sick, Avoid Enteral Feedings (Oral and Tube)]]></PAGETITLE>
				</PAGE>

				<PAGE ID="M1L0T1P16_4" pageID="19" PAGETYPE = "staic" SHOWINMENU="" ISDISABLEINMENU="" XMLSRC="pages/Topic01/xml/T01P16.xml" PAGESRC="pages/Topic01/T01P16_4.html" AUDIODISABLE="" BACKDISABLE="" NEXTDISABLE="" TRANSCRIPTDISABLE="" PLAYPAUSEDISABLE="" ISSKILLCHECK="" MAXCONDITION="0" SHOWLOGO="F">
					<PAGETITLE><![CDATA[Guideline I: If Infant Is Sick, Avoid Enteral Feedings (Oral and Tube)]]></PAGETITLE>
				</PAGE>

				<PAGE ID="M1L0T1P16_10" PAGETYPE = "unlockedPage" pageID="20"  SHOWINMENU="" ISDISABLEINMENU="" XMLSRC="pages/Topic01/xml/T01P04.xml" PAGESRC="pages/Topic01/T01P16_10.html" AUDIODISABLE="" BACKDISABLE="" NEXTDISABLE="" TRANSCRIPTDISABLE="" PLAYPAUSEDISABLE="" ISSKILLCHECK="" MAXCONDITION="0" SHOWLOGO="F">
					<PAGETITLE><![CDATA[Malrotation and Midgut Volvulus: Video]]></PAGETITLE>
				</PAGE>

				<PAGE ID="M1L0T1P17" pageID="21" PAGETYPE = "staic"  SHOWINMENU="" ISDISABLEINMENU="" XMLSRC="" PAGESRC="pages/Topic01/T01P17.html" AUDIODISABLE="" BACKDISABLE="" NEXTDISABLE="" TRANSCRIPTDISABLE="" PLAYPAUSEDISABLE="" ISSKILLCHECK="" MAXCONDITION="0" SHOWLOGO="F">
					<PAGETITLE><![CDATA[If Malrotation or Bowel Obstruction Is Suspected]]></PAGETITLE>
				</PAGE>

				<PAGE ID="M1L0T1P18" pageID="22" PAGETYPE = "staic" SHOWINMENU="" ISDISABLEINMENU="" XMLSRC="" PAGESRC="pages/Topic01/T01P18.html" AUDIODISABLE="" BACKDISABLE="" NEXTDISABLE="" TRANSCRIPTDISABLE="" PLAYPAUSEDISABLE="" ISSKILLCHECK="" MAXCONDITION="0" SHOWLOGO="F">
					<PAGETITLE><![CDATA[Glucose Is Essential for Normal Brain Function]]></PAGETITLE>
				</PAGE>

				<PAGE ID="M1L0T1P19" pageID="23" PAGETYPE = "staic" SHOWINMENU="" ISDISABLEINMENU="" XMLSRC="" PAGESRC="pages/Topic01/T01P19.html" AUDIODISABLE="" BACKDISABLE="" NEXTDISABLE="" TRANSCRIPTDISABLE="" PLAYPAUSEDISABLE="" ISSKILLCHECK="" MAXCONDITION="0" SHOWLOGO="F">
					<PAGETITLE><![CDATA[Guideline II: Quickly Establish IV Access and Provide Glucose via Intravenous (IV) Fluid]]></PAGETITLE>
				</PAGE>

				<PAGE ID="M1L0T1P20" pageID="24" PAGETYPE = "staic" SHOWINMENU="" ISDISABLEINMENU="" XMLSRC="" PAGESRC="pages/Topic01/T01P20.html" AUDIODISABLE="" BACKDISABLE="" NEXTDISABLE="" TRANSCRIPTDISABLE="" PLAYPAUSEDISABLE="" ISSKILLCHECK="" MAXCONDITION="0" SHOWLOGO="F">
					<PAGETITLE><![CDATA[Establishing Intravenous Access]]></PAGETITLE>
				</PAGE>

				<PAGE ID="M1L0T1P21" pageID="25"  PAGETYPE = "staic" SHOWINMENU="" ISDISABLEINMENU="" XMLSRC="" PAGESRC="pages/Topic01/T01P21.html" AUDIODISABLE="" BACKDISABLE="" NEXTDISABLE="" TRANSCRIPTDISABLE="" PLAYPAUSEDISABLE="" ISSKILLCHECK="" MAXCONDITION="0" SHOWLOGO="F">
					<PAGETITLE><![CDATA[Preparation for Extrauterine Life: Fetal Glucose Value]]></PAGETITLE>
				</PAGE>
				
				
				<PAGE ID="M1L0T1P22" pageID="26"  PAGETYPE = "staic" SHOWINMENU="" ISDISABLEINMENU="" XMLSRC="" PAGESRC="pages/Topic01/T01P22.html" AUDIODISABLE="" BACKDISABLE="" NEXTDISABLE="" TRANSCRIPTDISABLE="" PLAYPAUSEDISABLE="" ISSKILLCHECK="" MAXCONDITION="0" SHOWLOGO="F">
					<PAGETITLE><![CDATA[Preparation for Extrauterine Life]]></PAGETITLE><!--Slide 56-58 -->
				</PAGE>
				<PAGE ID="M1L0T1P23" pageID="27"  PAGETYPE = "staic" SHOWINMENU="" ISDISABLEINMENU="" XMLSRC="" PAGESRC="pages/Topic01/T01P23.html" AUDIODISABLE="" BACKDISABLE="" NEXTDISABLE="" TRANSCRIPTDISABLE="" PLAYPAUSEDISABLE="" ISSKILLCHECK="" MAXCONDITION="0" SHOWLOGO="F">
					<PAGETITLE><![CDATA[Glycogen Stores]]></PAGETITLE><!--Slide 59-64 -->
				</PAGE>
				<PAGE ID="M1L0T1P24" PAGETYPE = "unlockedPage" pageID="28"  SHOWINMENU="" ISDISABLEINMENU="" XMLSRC="" PAGESRC="pages/Topic01/T01P24.html" AUDIODISABLE="" BACKDISABLE="" NEXTDISABLE="" TRANSCRIPTDISABLE="" PLAYPAUSEDISABLE="" ISSKILLCHECK="" MAXCONDITION="0" SHOWLOGO="F">
					<PAGETITLE><![CDATA[Glycogen Stores: After Birth]]></PAGETITLE><!--Slide 65-66 -->
				</PAGE>
				<PAGE ID="M1L0T1P25" pageID="29" PAGETYPE = "staic"  SHOWINMENU="" ISDISABLEINMENU="" XMLSRC="" PAGESRC="pages/Topic01/T01P25.html" AUDIODISABLE="" BACKDISABLE="" NEXTDISABLE="" TRANSCRIPTDISABLE="" PLAYPAUSEDISABLE="" ISSKILLCHECK="" MAXCONDITION="0" SHOWLOGO="F">
					<PAGETITLE><![CDATA[Factors Impacting Glucose Levels]]></PAGETITLE><!--Slide 67 -->
				</PAGE>
				<PAGE ID="M1L0T1P26" pageID="30"  PAGETYPE = "staic" SHOWINMENU="" ISDISABLEINMENU="" XMLSRC="" PAGESRC="pages/Topic01/T01P26.html" AUDIODISABLE="" BACKDISABLE="" NEXTDISABLE="" TRANSCRIPTDISABLE="" PLAYPAUSEDISABLE="" ISSKILLCHECK="" MAXCONDITION="0" SHOWLOGO="F">
					<PAGETITLE><![CDATA[Inadequate Glycogen Stores: Preterm Infants]]></PAGETITLE><!--Slide 68-70 -->
				</PAGE>
				<PAGE ID="M1L0T1P27" PAGETYPE = "unlockedPage" pageID="31"  SHOWINMENU="" ISDISABLEINMENU="" XMLSRC="" PAGESRC="pages/Topic01/T01P27.html" AUDIODISABLE="" BACKDISABLE="" NEXTDISABLE="" TRANSCRIPTDISABLE="" PLAYPAUSEDISABLE="" ISSKILLCHECK="" MAXCONDITION="0" SHOWLOGO="F">
					<PAGETITLE><![CDATA[Inadequate Glycogen Stores: Preterm Infants]]></PAGETITLE><!--Slide 71 -->
				</PAGE>
				<PAGE ID="M1L0T1P28" pageID="32" PAGETYPE = "staic"  SHOWINMENU="" ISDISABLEINMENU="" XMLSRC="" PAGESRC="pages/Topic01/T01P28.html" AUDIODISABLE="" BACKDISABLE="" NEXTDISABLE="" TRANSCRIPTDISABLE="" PLAYPAUSEDISABLE="" ISSKILLCHECK="" MAXCONDITION="0" SHOWLOGO="F">
					<PAGETITLE><![CDATA[Inadequate Glycogen Stores: Late Preterm Infants]]></PAGETITLE><!--Slide 72-74 -->
				</PAGE>
				<PAGE ID="M1L0T1P29" pageID="33" PAGETYPE = "staic" SHOWINMENU="" ISDISABLEINMENU="" XMLSRC="" PAGESRC="pages/Topic01/T01P29.html" AUDIODISABLE="" BACKDISABLE="" NEXTDISABLE="" TRANSCRIPTDISABLE="" PLAYPAUSEDISABLE="" ISSKILLCHECK="" MAXCONDITION="0" SHOWLOGO="F">
					<PAGETITLE><![CDATA[Inadequate Glycogen Stores: Small for Gestational Age (SGA) Infants]]></PAGETITLE><!--Slide 75-77 -->
				</PAGE>
				<PAGE ID="M1L0T1P30" pageID="34"  PAGETYPE = "staic" SHOWINMENU="" ISDISABLEINMENU="" XMLSRC="" PAGESRC="pages/Topic01/T01P30.html" AUDIODISABLE="" BACKDISABLE="" NEXTDISABLE="" TRANSCRIPTDISABLE="" PLAYPAUSEDISABLE="" ISSKILLCHECK="" MAXCONDITION="0" SHOWLOGO="F">
					<PAGETITLE><![CDATA[Case Review: Baby Mateo]]></PAGETITLE><!--Slide 78-80 -->
				</PAGE>
				<PAGE ID="M1L0T1P31" pageID="35"  PAGETYPE = "staic" SHOWINMENU="" ISDISABLEINMENU="" XMLSRC="" PAGESRC="pages/Topic01/T01P31.html" AUDIODISABLE="" BACKDISABLE="" NEXTDISABLE="" TRANSCRIPTDISABLE="" PLAYPAUSEDISABLE="" ISSKILLCHECK="" MAXCONDITION="0" SHOWLOGO="F">
					<PAGETITLE><![CDATA[Case Review: Baby Mateo]]></PAGETITLE><!--Slide 81-83 -->
				</PAGE>
				<PAGE ID="M1L0T1P32" pageID="36" PAGETYPE = "staic"  SHOWINMENU="" ISDISABLEINMENU="" XMLSRC="" PAGESRC="pages/Topic01/T01P32.html" AUDIODISABLE="" BACKDISABLE="" NEXTDISABLE="" TRANSCRIPTDISABLE="" PLAYPAUSEDISABLE="" ISSKILLCHECK="" MAXCONDITION="0" SHOWLOGO="F">
					<PAGETITLE><![CDATA[Inadequate Glycogen Stores: Small for Gestational Age (SGA) Infants (II)]]></PAGETITLE><!--Slide 84-87 -->
				</PAGE>
				<PAGE ID="M1L0T1P33" pageID="37" PAGETYPE = "staic" SHOWINMENU="" ISDISABLEINMENU="" XMLSRC="" PAGESRC="pages/Topic01/T01P33.html" AUDIODISABLE="" BACKDISABLE="" NEXTDISABLE="" TRANSCRIPTDISABLE="" PLAYPAUSEDISABLE="" ISSKILLCHECK="" MAXCONDITION="0" SHOWLOGO="F">
					<PAGETITLE><![CDATA[Case Review: Baby Mateo]]></PAGETITLE><!--Slide 88-90 -->
				</PAGE>
				<PAGE ID="M1L0T1P34" pageID="38" PAGETYPE = "staic" SHOWINMENU="" ISDISABLEINMENU="" XMLSRC="" PAGESRC="pages/Topic01/T01P34.html" AUDIODISABLE="" BACKDISABLE="" NEXTDISABLE="" TRANSCRIPTDISABLE="" PLAYPAUSEDISABLE="" ISSKILLCHECK="" MAXCONDITION="0" SHOWLOGO="F">
					<PAGETITLE><![CDATA[Case Review: Baby Mateo]]></PAGETITLE><!--Slide 91-93 -->
				</PAGE>
				<PAGE ID="M1L0T1P35" PAGETYPE = "unlockedPage"  pageID="39"  SHOWINMENU="" ISDISABLEINMENU="" XMLSRC="" PAGESRC="pages/Topic01/T01P35.html" AUDIODISABLE="" BACKDISABLE="" NEXTDISABLE="" TRANSCRIPTDISABLE="" PLAYPAUSEDISABLE="" ISSKILLCHECK="" MAXCONDITION="0" SHOWLOGO="F">
					<PAGETITLE><![CDATA[Factors Impacting Glucose Levels: Hyperinsulinemia]]></PAGETITLE><!--Slide 94 -->
				</PAGE>
				<PAGE ID="M1L0T1P35_1" pageID="40" PAGETYPE = "staic"  SHOWINMENU="" ISDISABLEINMENU="" XMLSRC="" PAGESRC="pages/Topic01/T01P35_1.html" AUDIODISABLE="" BACKDISABLE="" NEXTDISABLE="" TRANSCRIPTDISABLE="" PLAYPAUSEDISABLE="" ISSKILLCHECK="" MAXCONDITION="0" SHOWLOGO="F">
					<PAGETITLE><![CDATA[Factors Impacting Glucose Levels: Hyperinsulinemia in IDM Infants]]></PAGETITLE><!--Slide 95-97 -->
				</PAGE>
				<PAGE ID="M1L0T1P35_2" pageID="41" PAGETYPE = "staic" SHOWINMENU="" ISDISABLEINMENU="" XMLSRC="" PAGESRC="pages/Topic01/T01P35_2.html" AUDIODISABLE="" BACKDISABLE="" NEXTDISABLE="" TRANSCRIPTDISABLE="" PLAYPAUSEDISABLE="" ISSKILLCHECK="" MAXCONDITION="0" SHOWLOGO="F">
					<PAGETITLE><![CDATA[Types of Diabetes]]></PAGETITLE><!--Slide 98-101 -->
				</PAGE>
				<PAGE ID="M1L0T1P36" pageID="42" PAGETYPE = "staic"  SHOWINMENU="" ISDISABLEINMENU="" XMLSRC="" PAGESRC="pages/Topic01/T01P36.html" AUDIODISABLE="" BACKDISABLE="" NEXTDISABLE="" TRANSCRIPTDISABLE="" PLAYPAUSEDISABLE="" ISSKILLCHECK="" MAXCONDITION="0" SHOWLOGO="F">
					<PAGETITLE><![CDATA[Diabetic Women of Childbearing Age]]></PAGETITLE><!--Slide 102 -->
				</PAGE>
				<PAGE ID="M1L0T1P37" pageID="43" PAGETYPE = "staic" SHOWINMENU="" ISDISABLEINMENU="" XMLSRC="" PAGESRC="pages/Topic01/T01P37.html" AUDIODISABLE="" BACKDISABLE="" NEXTDISABLE="" TRANSCRIPTDISABLE="" PLAYPAUSEDISABLE="" ISSKILLCHECK="" MAXCONDITION="0" SHOWLOGO="F">
					<PAGETITLE><![CDATA[Large for Gestational Age Infants]]></PAGETITLE><!--Slide 103-105 -->
				</PAGE>
				<PAGE ID="M1L0T1P38" pageID="44"  PAGETYPE = "staic" SHOWINMENU="" ISDISABLEINMENU="" XMLSRC="" PAGESRC="pages/Topic01/T01P38.html" AUDIODISABLE="" BACKDISABLE="" NEXTDISABLE="" TRANSCRIPTDISABLE="" PLAYPAUSEDISABLE="" ISSKILLCHECK="" MAXCONDITION="0" SHOWLOGO="F">
					<PAGETITLE><![CDATA[Macrosomic Infants]]></PAGETITLE><!--Slide 106-108 -->
				</PAGE>
				<PAGE ID="M1L0T1P39" pageID="45" PAGETYPE = "staic"  SHOWINMENU="" ISDISABLEINMENU="" XMLSRC="" PAGESRC="pages/Topic01/T01P39.html" AUDIODISABLE="" BACKDISABLE="" NEXTDISABLE="" TRANSCRIPTDISABLE="" PLAYPAUSEDISABLE="" ISSKILLCHECK="" MAXCONDITION="0" SHOWLOGO="F">
					<PAGETITLE><![CDATA[Injuries Associated with Macrosomic Infants]]></PAGETITLE><!--Slide 109 -->
				</PAGE>
				<PAGE ID="M1L0T1P40" pageID="46" PAGETYPE = "staic" SHOWINMENU="" ISDISABLEINMENU="" XMLSRC="" PAGESRC="pages/Topic01/T01P40.html" AUDIODISABLE="" BACKDISABLE="" NEXTDISABLE="" TRANSCRIPTDISABLE="" PLAYPAUSEDISABLE="" ISSKILLCHECK="" MAXCONDITION="0" SHOWLOGO="F">
					<PAGETITLE><![CDATA[Case Review: Baby Conrad]]></PAGETITLE><!--Slide 110-112 -->
				</PAGE>
				<PAGE ID="M1L0T1P41" pageID="47" PAGETYPE = "staic" SHOWINMENU="" ISDISABLEINMENU="" XMLSRC="" PAGESRC="pages/Topic01/T01P41.html" AUDIODISABLE="" BACKDISABLE="" NEXTDISABLE="" TRANSCRIPTDISABLE="" PLAYPAUSEDISABLE="" ISSKILLCHECK="" MAXCONDITION="0" SHOWLOGO="F">
					<PAGETITLE><![CDATA[Case Review: Baby Conrad]]></PAGETITLE><!--Slide 113-115 -->
				</PAGE>
				<PAGE ID="M1L0T1P42" pageID="48" PAGETYPE = "staic"  SHOWINMENU="" ISDISABLEINMENU="" XMLSRC="" PAGESRC="pages/Topic01/T01P42.html" AUDIODISABLE="" BACKDISABLE="" NEXTDISABLE="" TRANSCRIPTDISABLE="" PLAYPAUSEDISABLE="" ISSKILLCHECK="" MAXCONDITION="0" SHOWLOGO="F">
					<PAGETITLE><![CDATA[Factors Impacting Glucose Levels: Increased Glucose Utilization]]></PAGETITLE><!--Slide 116 -->
				</PAGE>
				<PAGE ID="M1L0T1P43" pageID="49" PAGETYPE = "staic"  SHOWINMENU="" ISDISABLEINMENU="" XMLSRC="" PAGESRC="pages/Topic01/T01P44.html" AUDIODISABLE="" BACKDISABLE="" NEXTDISABLE="" TRANSCRIPTDISABLE="" PLAYPAUSEDISABLE="" ISSKILLCHECK="" MAXCONDITION="0" SHOWLOGO="F">
					<PAGETITLE><![CDATA[Aerobic and Anaerobic Metabolism]]></PAGETITLE><!--Slide 118 -->
				</PAGE>
				<PAGE ID="M1L0T1P44" PAGETYPE = "unlockedPage" pageID="50"  SHOWINMENU="" ISDISABLEINMENU="" XMLSRC="" PAGESRC="pages/Topic01/T01P43.html" AUDIODISABLE="" BACKDISABLE="" NEXTDISABLE="" TRANSCRIPTDISABLE="" PLAYPAUSEDISABLE="" ISSKILLCHECK="" MAXCONDITION="0" SHOWLOGO="F">
					<PAGETITLE><![CDATA[Aerobic and Anaerobic Metabolism: Video]]></PAGETITLE><!--Slide 117 -->
				</PAGE>				
				<PAGE ID="M1L0T1P45" pageID="51"  PAGETYPE = "staic" SHOWINMENU="" ISDISABLEINMENU="" XMLSRC="" PAGESRC="pages/Topic01/T01P45.html" AUDIODISABLE="" BACKDISABLE="" NEXTDISABLE="" TRANSCRIPTDISABLE="" PLAYPAUSEDISABLE="" ISSKILLCHECK="" MAXCONDITION="0" SHOWLOGO="F">
					<PAGETITLE><![CDATA[Review: Risk Factors for Hypoglycemia]]></PAGETITLE> <!-- Slide 119-121  -->
				</PAGE>				
				<!-- Today first 20 pages -->	
				<PAGE ID="M1L0T1P46" pageID="52" PAGETYPE = "staic"  SHOWINMENU="" ISDISABLEINMENU="" XMLSRC="" PAGESRC="pages/Topic01/T01P46.html" AUDIODISABLE="" BACKDISABLE="" NEXTDISABLE="" TRANSCRIPTDISABLE="" PLAYPAUSEDISABLE="" ISSKILLCHECK="" MAXCONDITION="0" SHOWLOGO="F">
					<PAGETITLE><![CDATA[Definition of Hypoglycemia]]></PAGETITLE><!--Slide 122 -->
				</PAGE>
				<PAGE ID="M1L0T1P47" pageID="53" PAGETYPE = "staic"  SHOWINMENU="" ISDISABLEINMENU="" XMLSRC="" PAGESRC="pages/Topic01/T01P47.html" AUDIODISABLE="" BACKDISABLE="" NEXTDISABLE="" TRANSCRIPTDISABLE="" PLAYPAUSEDISABLE="" ISSKILLCHECK="" MAXCONDITION="0" SHOWLOGO="F">
					<PAGETITLE><![CDATA[Signs and Symptoms of Hypoglycemia]]></PAGETITLE><!--Slide 123-124 -->
				</PAGE>
				<PAGE ID="M1L0T1P48" pageID="54" PAGETYPE = "staic"  SHOWINMENU="" ISDISABLEINMENU="" XMLSRC="" PAGESRC="pages/Topic01/T01P48.html" AUDIODISABLE="" BACKDISABLE="" NEXTDISABLE="" TRANSCRIPTDISABLE="" PLAYPAUSEDISABLE="" ISSKILLCHECK="" MAXCONDITION="0" SHOWLOGO="F">
					<PAGETITLE><![CDATA[Asymptomatic Hypoglycemia]]></PAGETITLE><!--Slide 125 -->
				</PAGE>

				<PAGE ID="M1L0T1P49" pageID="55" PAGETYPE = "staic"  SHOWINMENU="" ISDISABLEINMENU="" XMLSRC="" PAGESRC="pages/Topic01/T01P49.html" AUDIODISABLE="" BACKDISABLE="" NEXTDISABLE="" TRANSCRIPTDISABLE="" PLAYPAUSEDISABLE="" ISSKILLCHECK="" MAXCONDITION="0" SHOWLOGO="F">
					<PAGETITLE><![CDATA[Blood Sugar Monitoring]]></PAGETITLE><!--Slide 126-127 -->
				</PAGE>

				<PAGE ID="M1L0T1P51" pageID="56"  PAGETYPE = "staic" SHOWINMENU="" ISDISABLEINMENU="" XMLSRC="" PAGESRC="pages/Topic01/T01P51.html" AUDIODISABLE="" BACKDISABLE="" NEXTDISABLE="" TRANSCRIPTDISABLE="" PLAYPAUSEDISABLE="" ISSKILLCHECK="" MAXCONDITION="0" SHOWLOGO="F">
					<PAGETITLE><![CDATA[Target Glucose Level: Sick Infants Requiring Intensive Care]]></PAGETITLE><!--Slide 129 -->
				</PAGE>

				<PAGE ID="M1L0T1P50" pageID="57" PAGETYPE = "staic"  SHOWINMENU="" ISDISABLEINMENU="" XMLSRC="" PAGESRC="pages/Topic01/T01P50.html" AUDIODISABLE="" BACKDISABLE="" NEXTDISABLE="" TRANSCRIPTDISABLE="" PLAYPAUSEDISABLE="" ISSKILLCHECK="" MAXCONDITION="0" SHOWLOGO="F">
					<PAGETITLE><![CDATA[Time Intervals for Evaluating Blood Sugar]]></PAGETITLE><!--Slide 128 -->
				</PAGE>

			
				<PAGE ID="M1L0T1P52" pageID="58" PAGETYPE = "staic"  SHOWINMENU="" ISDISABLEINMENU="" XMLSRC="" PAGESRC="pages/Topic01/T01P52.html" AUDIODISABLE="" BACKDISABLE="" NEXTDISABLE="" TRANSCRIPTDISABLE="" PLAYPAUSEDISABLE="" ISSKILLCHECK="" MAXCONDITION="0" SHOWLOGO="F">
					<PAGETITLE><![CDATA[Plasma Glucose Value]]></PAGETITLE><!--Slide 130 -->
				</PAGE>

				<PAGE ID="M1L0T1P53" pageID="59" PAGETYPE = "staic"  SHOWINMENU="" ISDISABLEINMENU="" XMLSRC="" PAGESRC="pages/Topic01/T01P53.html" AUDIODISABLE="" BACKDISABLE="" NEXTDISABLE="" TRANSCRIPTDISABLE="" PLAYPAUSEDISABLE="" ISSKILLCHECK="" MAXCONDITION="0" SHOWLOGO="F">
					<PAGETITLE><![CDATA[Point-of-Care Testing]]></PAGETITLE><!--Slide 131 -->
				</PAGE>

				<PAGE ID="M1L0T1P54" pageID="60" PAGETYPE = "staic"  SHOWINMENU="" ISDISABLEINMENU="" XMLSRC="" PAGESRC="pages/Topic01/T01P54.html" AUDIODISABLE="" BACKDISABLE="" NEXTDISABLE="" TRANSCRIPTDISABLE="" PLAYPAUSEDISABLE="" ISSKILLCHECK="" MAXCONDITION="0" SHOWLOGO="F">
					<PAGETITLE><![CDATA[Initial IV Fluid and Rate]]></PAGETITLE><!-- -->
				</PAGE>

				<PAGE ID="M1L0T1P55" pageID="61" PAGETYPE = "staic"  SHOWINMENU="" ISDISABLEINMENU="" XMLSRC="" PAGESRC="pages/Topic01/T01P55.html" AUDIODISABLE="" BACKDISABLE="" NEXTDISABLE="" TRANSCRIPTDISABLE="" PLAYPAUSEDISABLE="" ISSKILLCHECK="" MAXCONDITION="0" SHOWLOGO="F">
					<PAGETITLE><![CDATA[Calculating IV Fluid Rates]]></PAGETITLE><!--Slide 133 -->
				</PAGE>

				<PAGE ID="M1L0T1P56" pageID="62" PAGETYPE = "staic"  SHOWINMENU="" ISDISABLEINMENU="" XMLSRC="" PAGESRC="pages/Topic01/T01P56.html" AUDIODISABLE="" BACKDISABLE="" NEXTDISABLE="" TRANSCRIPTDISABLE="" PLAYPAUSEDISABLE="" ISSKILLCHECK="" MAXCONDITION="0" SHOWLOGO="F">
					<PAGETITLE><![CDATA[Case Review: Baby Mateo]]></PAGETITLE><!--Slide 134-136 -->
				</PAGE>

				<PAGE ID="M1L0T1P57" pageID="63" PAGETYPE = "staic" SHOWINMENU="" ISDISABLEINMENU="" XMLSRC="" PAGESRC="pages/Topic01/T01P57.html" AUDIODISABLE="" BACKDISABLE="" NEXTDISABLE="" TRANSCRIPTDISABLE="" PLAYPAUSEDISABLE="" ISSKILLCHECK="" MAXCONDITION="0" SHOWLOGO="F">
					<PAGETITLE><![CDATA[Case Review: Baby Mateo]]></PAGETITLE><!--Slide 137-139 -->
				</PAGE>

				<PAGE ID="M1L0T1P58" pageID="64" PAGETYPE = "staic" SHOWINMENU="" ISDISABLEINMENU="" XMLSRC="" PAGESRC="pages/Topic01/T01P58.html" AUDIODISABLE="" BACKDISABLE="" NEXTDISABLE="" TRANSCRIPTDISABLE="" PLAYPAUSEDISABLE="" ISSKILLCHECK="" MAXCONDITION="0" SHOWLOGO="F">
					<PAGETITLE><![CDATA[Case Review: Baby Mateo]]></PAGETITLE><!--Slide 140-142 -->
				</PAGE>

				<PAGE ID="M1L0T1P59" pageID="65" PAGETYPE = "staic" SHOWINMENU="" ISDISABLEINMENU="" XMLSRC="" PAGESRC="pages/Topic01/T01P59.html" AUDIODISABLE="" BACKDISABLE="" NEXTDISABLE="" TRANSCRIPTDISABLE="" PLAYPAUSEDISABLE="" ISSKILLCHECK="" MAXCONDITION="0" SHOWLOGO="F">
					<PAGETITLE><![CDATA[Case Review: Baby Conrad]]></PAGETITLE><!--Slide 143-145 -->
				</PAGE>

				<PAGE ID="M1L0T1P60" pageID="66"  PAGETYPE = "staic" SHOWINMENU="" ISDISABLEINMENU="" XMLSRC="" PAGESRC="pages/Topic01/T01P60.html" AUDIODISABLE="" BACKDISABLE="" NEXTDISABLE="" TRANSCRIPTDISABLE="" PLAYPAUSEDISABLE="" ISSKILLCHECK="" MAXCONDITION="0" SHOWLOGO="F">
					<PAGETITLE><![CDATA[Case Review: Baby Conrad]]></PAGETITLE><!--Slide 146-148 -->
				</PAGE>

				<PAGE ID="M1L0T1P61" pageID="67" PAGETYPE = "staic" SHOWINMENU="" ISDISABLEINMENU="" XMLSRC="" PAGESRC="pages/Topic01/T01P61.html" AUDIODISABLE="" BACKDISABLE="" NEXTDISABLE="" TRANSCRIPTDISABLE="" PLAYPAUSEDISABLE="" ISSKILLCHECK="" MAXCONDITION="0" SHOWLOGO="F">
					<PAGETITLE><![CDATA[Case Review: Baby Conrad]]></PAGETITLE><!--Slide 149-151 -->
				</PAGE>

				<PAGE ID="M1L0T1P62" pageID="68" PAGETYPE = "staic" SHOWINMENU="" ISDISABLEINMENU="" XMLSRC="" PAGESRC="pages/Topic01/T01P62.html" AUDIODISABLE="" BACKDISABLE="" NEXTDISABLE="" TRANSCRIPTDISABLE="" PLAYPAUSEDISABLE="" ISSKILLCHECK="" MAXCONDITION="0" SHOWLOGO="F">
					<PAGETITLE><![CDATA[Case Review: Baby Conrad]]></PAGETITLE><!--Slide 152-154 -->
				</PAGE>

				<PAGE ID="M1L0T1P63" pageID="69" PAGETYPE = "staic" SHOWINMENU="" ISDISABLEINMENU="" XMLSRC="" PAGESRC="pages/Topic01/T01P63.html" AUDIODISABLE="" BACKDISABLE="" NEXTDISABLE="" TRANSCRIPTDISABLE="" PLAYPAUSEDISABLE="" ISSKILLCHECK="" MAXCONDITION="0" SHOWLOGO="F">
					<PAGETITLE><![CDATA[Case Review: Baby Conrad]]></PAGETITLE><!--Slide 155-157 -->
				</PAGE>

				<PAGE ID="M1L0T1P64" pageID="70" PAGETYPE = "staic" SHOWINMENU="" ISDISABLEINMENU="" XMLSRC="" PAGESRC="pages/Topic01/T01P64.html" AUDIODISABLE="" BACKDISABLE="" NEXTDISABLE="" TRANSCRIPTDISABLE="" PLAYPAUSEDISABLE="" ISSKILLCHECK="" MAXCONDITION="0" SHOWLOGO="F">
					<PAGETITLE><![CDATA[Case Review: Baby Conrad]]></PAGETITLE><!--Slide 158-160 -->
				</PAGE>

				<PAGE ID="M1L0T1P65" pageID="71" PAGETYPE = "staic" SHOWINMENU="" ISDISABLEINMENU="" XMLSRC="" PAGESRC="pages/Topic01/T01P65.html" AUDIODISABLE="" BACKDISABLE="" NEXTDISABLE="" TRANSCRIPTDISABLE="" PLAYPAUSEDISABLE="" ISSKILLCHECK="" MAXCONDITION="0" SHOWLOGO="F">
					<PAGETITLE><![CDATA[Case Review: Baby Conrad]]></PAGETITLE><!--Slide 161-163 -->
				</PAGE>

				<PAGE ID="M1L0T1P66" pageID="72" PAGETYPE = "staic" SHOWINMENU="" ISDISABLEINMENU="" XMLSRC="" PAGESRC="pages/Topic01/T01P66.html" AUDIODISABLE="" BACKDISABLE="" NEXTDISABLE="" TRANSCRIPTDISABLE="" PLAYPAUSEDISABLE="" ISSKILLCHECK="" MAXCONDITION="0" SHOWLOGO="F">
					<PAGETITLE><![CDATA[Case Review: Baby Conrad]]></PAGETITLE><!--Slide 164-166 -->
				</PAGE>
				
				<PAGE ID="M1L0T1P67" pageID="73" PAGETYPE = "staic" SHOWINMENU="" ISDISABLEINMENU="" XMLSRC="" PAGESRC="pages/Topic01/T01P67.html" AUDIODISABLE="" BACKDISABLE="" NEXTDISABLE="" TRANSCRIPTDISABLE="" PLAYPAUSEDISABLE="" ISSKILLCHECK="" MAXCONDITION="0" SHOWLOGO="F">
					<PAGETITLE><![CDATA[Blood Sugar Monitoring: Activity]]></PAGETITLE><!--Slide 167-170 -->
				</PAGE>				
				<!-- Today first 20 pages -->		

				<PAGE ID="M1L0T1P68" pageID="74"  PAGETYPE = "staic" SHOWINMENU="" ISDISABLEINMENU="" XMLSRC="" PAGESRC="pages/Topic01/T01P68.html" AUDIODISABLE="" BACKDISABLE="" NEXTDISABLE="" TRANSCRIPTDISABLE="" PLAYPAUSEDISABLE="" ISSKILLCHECK="" MAXCONDITION="0" SHOWLOGO="F">

					<PAGETITLE><![CDATA[IV Treatment of Hypoglycemia]]></PAGETITLE><!--Slide 171-175 -->

				</PAGE>

				<!--<PAGE ID="M1L0T1P69" pageID="1"  SHOWINMENU="" ISDISABLEINMENU="" XMLSRC="" PAGESRC="pages/Topic01/T01P69.html" AUDIODISABLE="" BACKDISABLE="" NEXTDISABLE="" TRANSCRIPTDISABLE="" PLAYPAUSEDISABLE="" ISSKILLCHECK="" MAXCONDITION="0" SHOWLOGO="F">

					<PAGETITLE><![CDATA[Treatment of Hypoglycemia]]></PAGETITLE>Slide 176-183 

				</PAGE>-->

				<PAGE ID="M1L0T1P70" pageID="75" PAGETYPE = "staic"  SHOWINMENU="" ISDISABLEINMENU="" XMLSRC="" PAGESRC="pages/Topic01/T01P70.html" AUDIODISABLE="" BACKDISABLE="" NEXTDISABLE="" TRANSCRIPTDISABLE="" PLAYPAUSEDISABLE="" ISSKILLCHECK="" MAXCONDITION="0" SHOWLOGO="F">

					<PAGETITLE><![CDATA[Treatment of Hypoglycemia: Complete Chart]]></PAGETITLE><!--Slide 184 -->

				</PAGE>

				<PAGE ID="M1L0T1P71" pageID="76" PAGETYPE = "staic"  SHOWINMENU="" ISDISABLEINMENU="" XMLSRC="" PAGESRC="pages/Topic01/T01P71.html" AUDIODISABLE="" BACKDISABLE="" NEXTDISABLE="" TRANSCRIPTDISABLE="" PLAYPAUSEDISABLE="" ISSKILLCHECK="" MAXCONDITION="0" SHOWLOGO="F">

					<PAGETITLE><![CDATA[If Blood Sugar Remains Persistently Low]]></PAGETITLE><!--Slide 185 -->

				</PAGE>

				<PAGE ID="M1L0T1P72" pageID="77"  PAGETYPE = "staic" SHOWINMENU="" ISDISABLEINMENU="" XMLSRC="" PAGESRC="pages/Topic01/T01P72.html" AUDIODISABLE="" BACKDISABLE="" NEXTDISABLE="" TRANSCRIPTDISABLE="" PLAYPAUSEDISABLE="" ISSKILLCHECK="" MAXCONDITION="0" SHOWLOGO="F">

					<PAGETITLE><![CDATA[Infants Healthy Enough to Feed]]></PAGETITLE><!--Slide 186-187 -->

				</PAGE>

				<PAGE ID="M1L0T1P73" pageID="78" PAGETYPE = "staic"  SHOWINMENU="" ISDISABLEINMENU="" XMLSRC="" PAGESRC="pages/Topic01/T01P73.html" AUDIODISABLE="" BACKDISABLE="" NEXTDISABLE="" TRANSCRIPTDISABLE="" PLAYPAUSEDISABLE="" ISSKILLCHECK="" MAXCONDITION="0" SHOWLOGO="F">

					<PAGETITLE><![CDATA[Umbilical Catheters: Introduction]]></PAGETITLE><!--Slide 188 -->

				</PAGE>

				<PAGE ID="M1L0T1P74" pageID="79" PAGETYPE = "staic"  SHOWINMENU="" ISDISABLEINMENU="" XMLSRC="" PAGESRC="pages/Topic01/T01P74.html" AUDIODISABLE="" BACKDISABLE="" NEXTDISABLE="" TRANSCRIPTDISABLE="" PLAYPAUSEDISABLE="" ISSKILLCHECK="" MAXCONDITION="0" SHOWLOGO="F">

					<PAGETITLE><![CDATA[Umbilical Catheters]]></PAGETITLE><!--Slide 189-191 -->

				</PAGE>

				<!--<PAGE ID="M1L0T1P75" pageID="1"  SHOWINMENU="" ISDISABLEINMENU="" XMLSRC="" PAGESRC="pages/Topic01/T01P75.html" AUDIODISABLE="" BACKDISABLE="" NEXTDISABLE="" TRANSCRIPTDISABLE="" PLAYPAUSEDISABLE="" ISSKILLCHECK="" MAXCONDITION="0" SHOWLOGO="F">

					<PAGETITLE><![CDATA[Umbilical Catheters: Medications]]></PAGETITLE>Slide 192-194 

				</PAGE>

				<PAGE ID="M1L0T1P76" pageID="1"  SHOWINMENU="" ISDISABLEINMENU="" XMLSRC="" PAGESRC="pages/Topic01/T01P76.html" AUDIODISABLE="" BACKDISABLE="" NEXTDISABLE="" TRANSCRIPTDISABLE="" PLAYPAUSEDISABLE="" ISSKILLCHECK="" MAXCONDITION="0" SHOWLOGO="F">

					<PAGETITLE><![CDATA[Umbilical Catheters: Contraindications]]></PAGETITLE>Slide 195-197 

				</PAGE>-->

				<PAGE ID="M1L0T1P77" pageID="80" PAGETYPE = "staic"  SHOWINMENU="" ISDISABLEINMENU="" XMLSRC="" PAGESRC="pages/Topic01/T01P77.html" AUDIODISABLE="" BACKDISABLE="" NEXTDISABLE="" TRANSCRIPTDISABLE="" PLAYPAUSEDISABLE="" ISSKILLCHECK="" MAXCONDITION="0" SHOWLOGO="F">

					<PAGETITLE><![CDATA[Umbilical Catheters: Heparin Safety]]></PAGETITLE><!--Slide 198 -->

				</PAGE>

				<PAGE ID="M1L0T1P78" pageID="81" PAGETYPE = "staic"  SHOWINMENU="" ISDISABLEINMENU="" XMLSRC="" PAGESRC="pages/Topic01/T01P78.html" AUDIODISABLE="" BACKDISABLE="" NEXTDISABLE="" TRANSCRIPTDISABLE="" PLAYPAUSEDISABLE="" ISSKILLCHECK="" MAXCONDITION="0" SHOWLOGO="F">

					<PAGETITLE><![CDATA[Umbilical Catheters: Safety Guidelines]]></PAGETITLE><!--Slide 199 -->

				</PAGE>

				<PAGE ID="M1L0T1P79" pageID="82" PAGETYPE = "staic"  SHOWINMENU="" ISDISABLEINMENU="" XMLSRC="" PAGESRC="pages/Topic01/T01P79.html" AUDIODISABLE="" BACKDISABLE="" NEXTDISABLE="" TRANSCRIPTDISABLE="" PLAYPAUSEDISABLE="" ISSKILLCHECK="" MAXCONDITION="0" SHOWLOGO="F">

					<PAGETITLE><![CDATA[Umbilical Catheters:  UAC Safety Guidelines]]></PAGETITLE><!--Slide 200 -->

				</PAGE>


				<!--<PAGE ID="M1L0T1P80" pageID="1"  SHOWINMENU="" ISDISABLEINMENU="" XMLSRC="" PAGESRC="pages/Topic01/T01P80.html" AUDIODISABLE="" BACKDISABLE="" NEXTDISABLE="" TRANSCRIPTDISABLE="" PLAYPAUSEDISABLE="" ISSKILLCHECK="" MAXCONDITION="0" SHOWLOGO="F">

					<PAGETITLE><![CDATA[Umbilical Catheters:  UAC Safety Guidelines (II)]]></PAGETITLE>

				</PAGE>-->
				

				<PAGE ID="M1L0T1P81" pageID="83" PAGETYPE = "staic"  SHOWINMENU="" ISDISABLEINMENU="" XMLSRC="" PAGESRC="pages/Topic01/T01P81.html" AUDIODISABLE="" BACKDISABLE="" NEXTDISABLE="" TRANSCRIPTDISABLE="" PLAYPAUSEDISABLE="" ISSKILLCHECK="" MAXCONDITION="0" SHOWLOGO="F">

					<PAGETITLE><![CDATA[Sugar and Safe Care: Key Points]]></PAGETITLE><!--Slide 202 -->

				</PAGE>

				<!--<PAGE ID="M1L0T1P82" pageID="1"  SHOWINMENU="" ISDISABLEINMENU="" XMLSRC="" PAGESRC="pages/Topic01/T01P82.html" AUDIODISABLE="" BACKDISABLE="" NEXTDISABLE="" TRANSCRIPTDISABLE="" PLAYPAUSEDISABLE="" ISSKILLCHECK="" MAXCONDITION="0" SHOWLOGO="F">

					<PAGETITLE><![CDATA[Sugar and Safe Care Assessments: Introduction]]></PAGETITLE>Slide 203 

				</PAGE>-->

				<PAGE ID="M1L0T1P82_1" pageID="84" PAGETYPE = "staic"  SHOWINMENU="" ISDISABLEINMENU="" XMLSRC="" PAGESRC="pages/Topic01/T01P82_1.html" AUDIODISABLE="" BACKDISABLE="" NEXTDISABLE="" TRANSCRIPTDISABLE="" PLAYPAUSEDISABLE="" ISSKILLCHECK="" MAXCONDITION="0" SHOWLOGO="F">

					<PAGETITLE><![CDATA[Sugar and Safe Care Assessments: Introduction]]></PAGETITLE><!--Slide 203 -->

				</PAGE>

				<PAGE ID="M1L0T1P83" PAGETYPE = "assessment" pageID="85"  SHOWINMENU="" ISDISABLEINMENU="" XMLSRC="" PAGESRC="pages/Topic01/T01P83.html" AUDIODISABLE="" BACKDISABLE="" NEXTDISABLE="" TRANSCRIPTDISABLE="" PLAYPAUSEDISABLE="" ISSKILLCHECK="" MAXCONDITION="0" SHOWLOGO="F">

					<PAGETITLE><![CDATA[Sugar and Safe Care Assessments]]></PAGETITLE><!--Slide 204-210 -->

				</PAGE>



				<PAGE ID="M1L0T1P84" PAGETYPE = "assessment" pageID="86"  SHOWINMENU="" ISDISABLEINMENU="" XMLSRC="" PAGESRC="pages/Topic01/T01P84.html" AUDIODISABLE="" BACKDISABLE="" NEXTDISABLE="" TRANSCRIPTDISABLE="" PLAYPAUSEDISABLE="" ISSKILLCHECK="" MAXCONDITION="0" SHOWLOGO="F">

					<PAGETITLE><![CDATA[Sugar and Safe Care Assessments]]></PAGETITLE><!--Slide 204-210 -->

				</PAGE>

				<PAGE ID="M1L0T1P85" PAGETYPE = "assessment" pageID="87"  SHOWINMENU="" ISDISABLEINMENU="" XMLSRC="" PAGESRC="pages/Topic01/T01P85.html" AUDIODISABLE="" BACKDISABLE="" NEXTDISABLE="" TRANSCRIPTDISABLE="" PLAYPAUSEDISABLE="" ISSKILLCHECK="" MAXCONDITION="0" SHOWLOGO="F">

					<PAGETITLE><![CDATA[Sugar and Safe Care Assessments]]></PAGETITLE><!--Slide 204-210 -->

				</PAGE>

				<PAGE ID="M1L0T1P86" PAGETYPE = "assessment" pageID="88"  SHOWINMENU="" ISDISABLEINMENU="" XMLSRC="" PAGESRC="pages/Topic01/T01P86.html" AUDIODISABLE="" BACKDISABLE="" NEXTDISABLE="" TRANSCRIPTDISABLE="" PLAYPAUSEDISABLE="" ISSKILLCHECK="" MAXCONDITION="0" SHOWLOGO="F">

					<PAGETITLE><![CDATA[Sugar and Safe Care Assessments]]></PAGETITLE><!--Slide 204-210 -->

				</PAGE>

				<PAGE ID="M1L0T1P87" PAGETYPE = "assessment" pageID="89"  SHOWINMENU="" ISDISABLEINMENU="" XMLSRC="" PAGESRC="pages/Topic01/T01P87.html" AUDIODISABLE="" BACKDISABLE="" NEXTDISABLE="" TRANSCRIPTDISABLE="" PLAYPAUSEDISABLE="" ISSKILLCHECK="" MAXCONDITION="0" SHOWLOGO="F">

					<PAGETITLE><![CDATA[Sugar and Safe Care Assessments]]></PAGETITLE><!--Slide 204-210 -->

				</PAGE>

				<PAGE ID="M1L0T1P88" PAGETYPE = "assessment" pageID="90"  SHOWINMENU="" ISDISABLEINMENU="" XMLSRC="" PAGESRC="pages/Topic01/T01P88.html" AUDIODISABLE="" BACKDISABLE="" NEXTDISABLE="" TRANSCRIPTDISABLE="" PLAYPAUSEDISABLE="" ISSKILLCHECK="" MAXCONDITION="0" SHOWLOGO="F">

					<PAGETITLE><![CDATA[Sugar and Safe Care Assessments]]></PAGETITLE><!--Slide 204-210 -->

				</PAGE>

				<PAGE ID="M1L0T1P89" PAGETYPE = "assessment" pageID="91"  SHOWINMENU="" ISDISABLEINMENU="" XMLSRC="" PAGESRC="pages/Topic01/T01P89.html" AUDIODISABLE="" BACKDISABLE="" NEXTDISABLE="" TRANSCRIPTDISABLE="" PLAYPAUSEDISABLE="" ISSKILLCHECK="" MAXCONDITION="0" SHOWLOGO="F">

					<PAGETITLE><![CDATA[Sugar and Safe Care Assessments]]></PAGETITLE><!--Slide 204-210 -->

				</PAGE>

				<PAGE ID="M1L0T1P96" PAGETYPE = "assessment" SHOWINMENU="N" ISDISABLEINMENU="" XMLSRC="" PAGESRC="pages/Topic01/T01P96.html" AUDIODISABLE="" BACKDISABLE="" NEXTDISABLE="" TRANSCRIPTDISABLE="" PLAYPAUSEDISABLE="" ISSKILLCHECK="" MAXCONDITION="0" SHOWLOGO="F">

					<PAGETITLE><![CDATA[Sugar and Safe Care: Result]]></PAGETITLE>

				</PAGE>

				<PAGE ID="M1L0T1P90" pageID="92" PAGETYPE = "staic"  SHOWINMENU="" ISDISABLEINMENU="" XMLSRC="" PAGESRC="pages/Topic01/T01P90.html" AUDIODISABLE="" BACKDISABLE="" NEXTDISABLE="" TRANSCRIPTDISABLE="" PLAYPAUSEDISABLE="" ISSKILLCHECK="" MAXCONDITION="0" SHOWLOGO="F">

					<PAGETITLE><![CDATA[Sugar and Safe Care: Conclusion]]></PAGETITLE><!--Slide 211 -->

				</PAGE>


				<PAGE ID="M1L0T1P91" pageID="93"  SHOWINMENU="" ISDISABLEINMENU="" XMLSRC="" PAGESRC="pages/Topic01/T01P91.html" AUDIODISABLE="" BACKDISABLE="" NEXTDISABLE="" TRANSCRIPTDISABLE="" PLAYPAUSEDISABLE="" ISSKILLCHECK="" MAXCONDITION="0" SHOWLOGO="F">

					<PAGETITLE><![CDATA[References]]></PAGETITLE>

					<!--Slide 123-124 -->

				</PAGE>

				<!--<PAGE ID="M1L0T1P91" pageID="1"  SHOWINMENU="" ISDISABLEINMENU="" XMLSRC="" PAGESRC="pages/Topic01/T01P91.html" AUDIODISABLE="" BACKDISABLE="" NEXTDISABLE="" TRANSCRIPTDISABLE="" PLAYPAUSEDISABLE="" ISSKILLCHECK="" MAXCONDITION="0" SHOWLOGO="F">

					<PAGETITLE><![CDATA[Calculating IV Fluid Rates]]></PAGETITLE>

				</PAGE>

				<PAGE ID="M1L0T1P92" pageID="1"  SHOWINMENU="" ISDISABLEINMENU="" XMLSRC="" PAGESRC="pages/Topic01/T01P92.html" AUDIODISABLE="" BACKDISABLE="" NEXTDISABLE="" TRANSCRIPTDISABLE="" PLAYPAUSEDISABLE="" ISSKILLCHECK="" MAXCONDITION="0" SHOWLOGO="F">

					<PAGETITLE><![CDATA[Calculating IV Fluid Rates]]></PAGETITLE>

				</PAGE>	

				<PAGE ID="M1L0T1P93" pageID="1"  SHOWINMENU="" ISDISABLEINMENU="" XMLSRC="" PAGESRC="pages/Topic01/T01P93.html" AUDIODISABLE="" BACKDISABLE="" NEXTDISABLE="" TRANSCRIPTDISABLE="" PLAYPAUSEDISABLE="" ISSKILLCHECK="" MAXCONDITION="0" SHOWLOGO="F">

					<PAGETITLE><![CDATA[Calculating IV Fluid Rates]]></PAGETITLE>

				</PAGE>	

				<PAGE ID="M1L0T1P94" pageID="1"  SHOWINMENU="" ISDISABLEINMENU="" XMLSRC="" PAGESRC="pages/Topic01/T01P94.html" AUDIODISABLE="" BACKDISABLE="" NEXTDISABLE="" TRANSCRIPTDISABLE="" PLAYPAUSEDISABLE="" ISSKILLCHECK="" MAXCONDITION="0" SHOWLOGO="F">

					<PAGETITLE><![CDATA[Calculating IV Fluid Rates]]></PAGETITLE>

				</PAGE>	-->
				
				
			</TOPIC>
		</LESSON>
	</MODULE>

	<GLOBAL>
		<!-- GLOBAL ATTRIBUTES AND CONSTANTS WILL BE LISTED HERE -->
	</GLOBAL>
	<PRELOADDATA>
		<!--<PreloadFile Path="media/images/BG_Image.jpg" />-->
		<PreloadFile Path="media/images/play_btn.png" />
		<PreloadFile Path="media/images/URL_Icon.png" />
		<PreloadFile Path="media/images/player/Help.png" />
		<PreloadFile Path="media/images/player/Instruction_icon.png" />
		<PreloadFile Path="media/images/player/menu_close.png" />
		<PreloadFile Path="media/images/player/mobile_icon.png" />
		<!-- <PreloadFile Path="media/images/player/pre_loder_01.gif" /> -->
		<PreloadFile Path="media/images/player/search_dwn.png" />
		<PreloadFile Path="media/images/player/search_nr.png" />
		<PreloadFile Path="media/images/player/tick.png" />
		<PreloadFile Path="media/images/player/Tick01.png" />
		<PreloadFile Path="media/images/player/browserZoom/chrome.png" />
		<PreloadFile Path="media/images/player/browserZoom/ie.png" />
		<PreloadFile Path="media/images/player/common/Additional-resources_outline.png" />
		<PreloadFile Path="media/images/player/common/audio_off_sprite.png" />
		<PreloadFile Path="media/images/player/common/audio_on_sprite.png" />
		<PreloadFile Path="media/images/player/common/back_sprite.png" />
		<PreloadFile Path="media/images/player/common/bg.png" />
		<PreloadFile Path="media/images/player/common/bottom_bar.png" />
		<PreloadFile Path="media/images/player/common/BTN_Back.png" />
		<PreloadFile Path="media/images/player/common/Exit_Sprite.png" />
		<PreloadFile Path="media/images/player/common/Glossary_Hover.png" />
		<PreloadFile Path="media/images/player/common/Glossary_normal.png" />
		<PreloadFile Path="media/images/player/common/help_sprite.png" />
		<PreloadFile Path="media/images/player/common/menu_sprite.png" />
		<PreloadFile Path="media/images/player/common/Next_GIF.gif" />
		<PreloadFile Path="media/images/player/common/next_sprite.png" />
		<PreloadFile Path="media/images/player/common/pause_sprite.png" />
		<PreloadFile Path="media/images/player/common/pinImg.png" />
		<PreloadFile Path="media/images/player/common/play_sprite.png" />
		<PreloadFile Path="media/images/player/common/replay_sprite.png" />
		<PreloadFile Path="media/images/player/common/Resources_Normal.png" />
		<PreloadFile Path="media/images/player/common/Resources_Over.png" />
		<PreloadFile Path="media/images/player/common/side_bar.png" />
		<PreloadFile Path="media/images/player/common/top_bar.png" />
		<PreloadFile Path="media/images/player/common/transcriptnormal_sprite.png" />
		<PreloadFile Path="media/images/player/common/Video_Resources_Normal.png" />
		<PreloadFile Path="media/images/player/common/Video_Resources_Over.png" />
		<PreloadFile Path="media/images/player/exit/line.png" />
		<PreloadFile Path="media/images/player/glossary/White_patch.png" />
		<PreloadFile Path="media/images/player/menu/Black_Complete.png" />
		<PreloadFile Path="media/images/player/menu/Menu_cover_sheen.png" />
		<PreloadFile Path="media/images/player/menu/White_Complete.png" />
		<PreloadFile Path="media/images/player/menu/White_Complete_Tick.png" />
		<PreloadFile Path="pages/images/Topic01/T01P01/module_objective_banner.png" />
		<!-- <PreloadFile Path="media/images/player/trans/TT_Base.png" /> -->
	</PRELOADDATA>
</COURSE>
